flask_ml/__init__.py
flask_ml/py.typed
flask_ml/flask_ml_cli/MLCli.py
flask_ml/flask_ml_cli/__init__.py
flask_ml/flask_ml_cli/utils.py
flask_ml/flask_ml_client/MLClient.py
flask_ml/flask_ml_client/__init__.py
flask_ml/flask_ml_server/MLServer.py
flask_ml/flask_ml_server/__init__.py
flask_ml/flask_ml_server/errors.py
flask_ml/flask_ml_server/models.py
flask_ml/flask_ml_server/openapi.yaml
flask_ml/flask_ml_server/templates.py
flask_ml/flask_ml_server/utils.py
flask_ml-0.2.3.dist-info/METADATA
flask_ml-0.2.3.dist-info/WHEEL
flask_ml-0.2.3.dist-info/licenses/LICENSE
flask_ml-0.2.3.dist-info/RECORD
