Metadata-Version: 2.3
Name: flask_ml
Version: 0.2.3
Summary: A Flask extension for running machine learning code
Project-URL: Homepage, https://github.com/UMass-Rescue/Flask-ML
Author-email: Prasanna Lakkur Subramanyam <psubramanyam@umass.edu>, Atharva Kale <aukale@umass.edu>, Shreyan Mallik <smallik@umass.edu>, Shriram Giridhara <sgiridhara@umass.edu>
License-File: LICENSE
Classifier: Environment :: Web Environment
Classifier: Intended Audience :: Developers
Classifier: License :: OSI Approved :: MIT License
Classifier: Operating System :: OS Independent
Classifier: Topic :: Internet :: WWW/HTTP :: Dynamic Content
Classifier: Topic :: Software Development :: Libraries :: Python Modules
Requires-Python: >=3.10
Requires-Dist: datamodel-code-generator
Requires-Dist: flask
Requires-Dist: pydantic
Requires-Dist: requests
Provides-Extra: dev
Requires-Dist: autoflake8; extra == 'dev'
Requires-Dist: black; extra == 'dev'
Requires-Dist: flake8; extra == 'dev'
Requires-Dist: isort; extra == 'dev'
Requires-Dist: mypy; extra == 'dev'
Requires-Dist: pytest; extra == 'dev'
Requires-Dist: pytest-cov; extra == 'dev'
Requires-Dist: types-requests; extra == 'dev'
